Metadata-Version: 1.2
Name: find-home
Version: 0.0.4
Summary: I just wanna find home...
Home-page: https://pypi.org/project/find_home/
Author: Vladimir Starostin
Author-email: vladimir.starostin@uni-tuebingen.de
License: MIT
Keywords: parser
Platform: UNKNOWN
Requires-Python: >=3.7.*
